archethic/__init__.py
archethic/api.py
archethic/crypto.py
archethic/keychain.py
archethic/transaction_builder.py
archethic/utils.py
tests/__init__.py
tests/test_crypto.py
tests/test_keychain.py
tests/test_transaction_builder.py
archethic-0.0.1.2.dist-info/METADATA
archethic-0.0.1.2.dist-info/WHEEL
archethic-0.0.1.2.dist-info/top_level.txt
archethic-0.0.1.2.dist-info/RECORD
