Metadata-Version: 2.1
Name: archethic
Version: 0.0.1.2
Summary: ArchEthic Python SDK
Home-page: https://github.com/aime-risson/archethic-python-sdk
Author: Aimé Risson
Author-email: aime.risson.1@gmail.fr
Keywords: python,crypto,archethic,python archethic,UCO
Classifier: Programming Language :: Python :: 3
Classifier: License :: OSI Approved :: MIT License
Classifier: Operating System :: OS Independent
Classifier: Intended Audience :: Education
Requires-Python: >=3.6
Requires-Dist: PyNaCl
Requires-Dist: libnacl
Requires-Dist: requests
Requires-Dist: pycryptodomex
Requires-Dist: gql
Requires-Dist: websockets
Requires-Dist: fastecdsa
Requires-Dist: secp256k1
Requires-Dist: requests-toolbelt
